{"a":[],"e":[],"f":[{"a":{"a":[]},"g":{"e":[]},"gen":false,"m":"SkipUnit","mut":false,"n":"XCTAssert","s":{"function":{"_0":[{"hasDefaultValue":false,"isInOut":false,"isVariadic":false,"isVariadicContinuation":false,"type":{"bool":{}}}],"_1":{"void":{}},"_2":0}},"sid":0,"t":{"functionDeclaration":{}},"v":{"available":{}},"z":{"f":false,"l":false,"m":false,"n":false,"o":false,"s":false,"sv":{"default":{}},"v":{"public":{}}}},{"a":{"a":[]},"g":{"e":[]},"gen":false,"m":"SkipUnit","mut":false,"n":"XCTAssertTrue","s":{"function":{"_0":[{"hasDefaultValue":false,"isInOut":false,"isVariadic":false,"isVariadicContinuation":false,"type":{"bool":{}}},{"hasDefaultValue":true,"isInOut":false,"isVariadic":false,"isVariadicContinuation":false,"type":{"string":{}}}],"_1":{"void":{}},"_2":0}},"sid":0,"t":{"functionDeclaration":{}},"v":{"available":{}},"z":{"f":false,"l":false,"m":false,"n":false,"o":false,"s":false,"sv":{"default":{}},"v":{"public":{}}}},{"a":{"a":[]},"g":{"e":[]},"gen":false,"m":"SkipUnit","mut":false,"n":"XCTAssertFalse","s":{"function":{"_0":[{"hasDefaultValue":false,"isInOut":false,"isVariadic":false,"isVariadicContinuation":false,"type":{"bool":{}}},{"hasDefaultValue":true,"isInOut":false,"isVariadic":false,"isVariadicContinuation":false,"type":{"string":{}}}],"_1":{"void":{}},"_2":0}},"sid":0,"t":{"functionDeclaration":{}},"v":{"available":{}},"z":{"f":false,"l":false,"m":false,"n":false,"o":false,"s":false,"sv":{"default":{}},"v":{"public":{}}}},{"a":{"a":[]},"g":{"e":[]},"gen":false,"m":"SkipUnit","mut":false,"n":"XCTAssertNil","s":{"function":{"_0":[{"hasDefaultValue":false,"isInOut":false,"isVariadic":false,"isVariadicContinuation":false,"type":{"optional":{"_0":{"any":{}}}}},{"hasDefaultValue":true,"isInOut":false,"isVariadic":false,"isVariadicContinuation":false,"type":{"string":{}}}],"_1":{"void":{}},"_2":0}},"sid":0,"t":{"functionDeclaration":{}},"v":{"available":{}},"z":{"f":false,"l":false,"m":false,"n":false,"o":false,"s":false,"sv":{"default":{}},"v":{"public":{}}}},{"a":{"a":[]},"g":{"e":[]},"gen":false,"m":"SkipUnit","mut":false,"n":"XCTAssertNotNil","s":{"function":{"_0":[{"hasDefaultValue":false,"isInOut":false,"isVariadic":false,"isVariadicContinuation":false,"type":{"optional":{"_0":{"any":{}}}}},{"hasDefaultValue":true,"isInOut":false,"isVariadic":false,"isVariadicContinuation":false,"type":{"string":{}}}],"_1":{"void":{}},"_2":0}},"sid":0,"t":{"functionDeclaration":{}},"v":{"available":{}},"z":{"f":false,"l":false,"m":false,"n":false,"o":false,"s":false,"sv":{"default":{}},"v":{"public":{}}}},{"a":{"a":[]},"g":{"e":[{"i":[],"n":"T"}]},"gen":false,"m":"SkipUnit","mut":false,"n":"XCTAssertIdentical","s":{"function":{"_0":[{"hasDefaultValue":false,"isInOut":false,"isVariadic":false,"isVariadicContinuation":false,"type":{"optional":{"_0":{"named":{"_0":"T","_1":[]}}}}},{"hasDefaultValue":false,"isInOut":false,"isVariadic":false,"isVariadicContinuation":false,"type":{"optional":{"_0":{"named":{"_0":"T","_1":[]}}}}},{"hasDefaultValue":true,"isInOut":false,"isVariadic":false,"isVariadicContinuation":false,"type":{"string":{}}}],"_1":{"void":{}},"_2":0}},"sid":0,"t":{"functionDeclaration":{}},"v":{"available":{}},"z":{"f":false,"l":false,"m":false,"n":false,"o":false,"s":false,"sv":{"default":{}},"v":{"public":{}}}},{"a":{"a":[]},"g":{"e":[{"i":[],"n":"T"}]},"gen":false,"m":"SkipUnit","mut":false,"n":"XCTAssertNotIdentical","s":{"function":{"_0":[{"hasDefaultValue":false,"isInOut":false,"isVariadic":false,"isVariadicContinuation":false,"type":{"optional":{"_0":{"named":{"_0":"T","_1":[]}}}}},{"hasDefaultValue":false,"isInOut":false,"isVariadic":false,"isVariadicContinuation":false,"type":{"optional":{"_0":{"named":{"_0":"T","_1":[]}}}}},{"hasDefaultValue":true,"isInOut":false,"isVariadic":false,"isVariadicContinuation":false,"type":{"string":{}}}],"_1":{"void":{}},"_2":0}},"sid":0,"t":{"functionDeclaration":{}},"v":{"available":{}},"z":{"f":false,"l":false,"m":false,"n":false,"o":false,"s":false,"sv":{"default":{}},"v":{"public":{}}}},{"a":{"a":[]},"g":{"e":[{"i":[],"n":"T"}]},"gen":false,"m":"SkipUnit","mut":false,"n":"XCTAssertEqual","s":{"function":{"_0":[{"hasDefaultValue":false,"isInOut":false,"isVariadic":false,"isVariadicContinuation":false,"type":{"optional":{"_0":{"named":{"_0":"T","_1":[]}}}}},{"hasDefaultValue":false,"isInOut":false,"isVariadic":false,"isVariadicContinuation":false,"type":{"optional":{"_0":{"named":{"_0":"T","_1":[]}}}}},{"hasDefaultValue":true,"isInOut":false,"isVariadic":false,"isVariadicContinuation":false,"type":{"string":{}}}],"_1":{"void":{}},"_2":0}},"sid":0,"t":{"functionDeclaration":{}},"v":{"available":{}},"z":{"f":false,"l":false,"m":false,"n":false,"o":false,"s":false,"sv":{"default":{}},"v":{"public":{}}}},{"a":{"a":[]},"g":{"e":[{"i":[],"n":"T"}]},"gen":false,"m":"SkipUnit","mut":false,"n":"XCTAssertNotEqual","s":{"function":{"_0":[{"hasDefaultValue":false,"isInOut":false,"isVariadic":false,"isVariadicContinuation":false,"type":{"optional":{"_0":{"named":{"_0":"T","_1":[]}}}}},{"hasDefaultValue":false,"isInOut":false,"isVariadic":false,"isVariadicContinuation":false,"type":{"optional":{"_0":{"named":{"_0":"T","_1":[]}}}}},{"hasDefaultValue":true,"isInOut":false,"isVariadic":false,"isVariadicContinuation":false,"type":{"string":{}}}],"_1":{"void":{}},"_2":0}},"sid":0,"t":{"functionDeclaration":{}},"v":{"available":{}},"z":{"f":false,"l":false,"m":false,"n":false,"o":false,"s":false,"sv":{"default":{}},"v":{"public":{}}}},{"a":{"a":[]},"g":{"e":[]},"gen":false,"m":"SkipUnit","mut":false,"n":"XCTAssertEqual","s":{"function":{"_0":[{"hasDefaultValue":false,"isInOut":false,"isVariadic":false,"isVariadicContinuation":false,"type":{"double":{}}},{"hasDefaultValue":false,"isInOut":false,"isVariadic":false,"isVariadicContinuation":false,"type":{"double":{}}},{"hasDefaultValue":false,"isInOut":false,"isVariadic":false,"isVariadicContinuation":false,"label":"accuracy","type":{"double":{}}},{"hasDefaultValue":true,"isInOut":false,"isVariadic":false,"isVariadicContinuation":false,"type":{"string":{}}}],"_1":{"void":{}},"_2":0}},"sid":0,"t":{"functionDeclaration":{}},"v":{"available":{}},"z":{"f":false,"l":false,"m":false,"n":false,"o":false,"s":false,"sv":{"default":{}},"v":{"public":{}}}},{"a":{"a":[]},"g":{"e":[]},"gen":false,"m":"SkipUnit","mut":false,"n":"XCTAssertEqual","s":{"function":{"_0":[{"hasDefaultValue":false,"isInOut":false,"isVariadic":false,"isVariadicContinuation":false,"type":{"float":{}}},{"hasDefaultValue":false,"isInOut":false,"isVariadic":false,"isVariadicContinuation":false,"type":{"float":{}}},{"hasDefaultValue":false,"isInOut":false,"isVariadic":false,"isVariadicContinuation":false,"label":"accuracy","type":{"float":{}}},{"hasDefaultValue":true,"isInOut":false,"isVariadic":false,"isVariadicContinuation":false,"type":{"string":{}}}],"_1":{"void":{}},"_2":0}},"sid":0,"t":{"functionDeclaration":{}},"v":{"available":{}},"z":{"f":false,"l":false,"m":false,"n":false,"o":false,"s":false,"sv":{"default":{}},"v":{"public":{}}}},{"a":{"a":[]},"g":{"e":[{"i":[],"n":"T"}]},"gen":false,"m":"SkipUnit","mut":false,"n":"XCTAssertGreaterThan","s":{"function":{"_0":[{"hasDefaultValue":false,"isInOut":false,"isVariadic":false,"isVariadicContinuation":false,"type":{"named":{"_0":"T","_1":[]}}},{"hasDefaultValue":false,"isInOut":false,"isVariadic":false,"isVariadicContinuation":false,"type":{"named":{"_0":"T","_1":[]}}},{"hasDefaultValue":true,"isInOut":false,"isVariadic":false,"isVariadicContinuation":false,"type":{"string":{}}}],"_1":{"void":{}},"_2":0}},"sid":0,"t":{"functionDeclaration":{}},"v":{"available":{}},"z":{"f":false,"l":false,"m":false,"n":false,"o":false,"s":false,"sv":{"default":{}},"v":{"public":{}}}},{"a":{"a":[]},"g":{"e":[{"i":[],"n":"T"}]},"gen":false,"m":"SkipUnit","mut":false,"n":"XCTAssertGreaterThanOrEqual","s":{"function":{"_0":[{"hasDefaultValue":false,"isInOut":false,"isVariadic":false,"isVariadicContinuation":false,"type":{"named":{"_0":"T","_1":[]}}},{"hasDefaultValue":false,"isInOut":false,"isVariadic":false,"isVariadicContinuation":false,"type":{"named":{"_0":"T","_1":[]}}},{"hasDefaultValue":true,"isInOut":false,"isVariadic":false,"isVariadicContinuation":false,"type":{"string":{}}}],"_1":{"void":{}},"_2":0}},"sid":0,"t":{"functionDeclaration":{}},"v":{"available":{}},"z":{"f":false,"l":false,"m":false,"n":false,"o":false,"s":false,"sv":{"default":{}},"v":{"public":{}}}},{"a":{"a":[]},"g":{"e":[{"i":[],"n":"T"}]},"gen":false,"m":"SkipUnit","mut":false,"n":"XCTAssertLessThan","s":{"function":{"_0":[{"hasDefaultValue":false,"isInOut":false,"isVariadic":false,"isVariadicContinuation":false,"type":{"named":{"_0":"T","_1":[]}}},{"hasDefaultValue":false,"isInOut":false,"isVariadic":false,"isVariadicContinuation":false,"type":{"named":{"_0":"T","_1":[]}}},{"hasDefaultValue":true,"isInOut":false,"isVariadic":false,"isVariadicContinuation":false,"type":{"string":{}}}],"_1":{"void":{}},"_2":0}},"sid":0,"t":{"functionDeclaration":{}},"v":{"available":{}},"z":{"f":false,"l":false,"m":false,"n":false,"o":false,"s":false,"sv":{"default":{}},"v":{"public":{}}}},{"a":{"a":[]},"g":{"e":[{"i":[],"n":"T"}]},"gen":false,"m":"SkipUnit","mut":false,"n":"XCTAssertLessThanOrEqual","s":{"function":{"_0":[{"hasDefaultValue":false,"isInOut":false,"isVariadic":false,"isVariadicContinuation":false,"type":{"named":{"_0":"T","_1":[]}}},{"hasDefaultValue":false,"isInOut":false,"isVariadic":false,"isVariadicContinuation":false,"type":{"named":{"_0":"T","_1":[]}}},{"hasDefaultValue":true,"isInOut":false,"isVariadic":false,"isVariadicContinuation":false,"type":{"string":{}}}],"_1":{"void":{}},"_2":0}},"sid":0,"t":{"functionDeclaration":{}},"v":{"available":{}},"z":{"f":false,"l":false,"m":false,"n":false,"o":false,"s":false,"sv":{"default":{}},"v":{"public":{}}}}],"m":"SkipUnit","stable":["/Users/paytondev/Documents/sharedqprotocol/.build/checkouts/skip-unit/Sources/SkipUnit/XCTest.swift"],"t":[],"v":[]}